{
    "products": [
      {
        "image": "photo_2023-05-27 21.40.11.jpeg",
        "imageS": "photo_2023-05-27 21.40.19.jpeg",
        "imageT": "photo_2023-05-27 21.40.21.jpeg",
        "name": "Стильний кардиган",
        "price": 600,
        "article": "0404",
        "available": true,
        "category": "Кардигани",
        "color": "Рожевий",
        "descF": "Машинна в'язка (70% акрил 30% вовна)",
        "descS": "Оne size 42-46",
        "descT": "Туреччина"
      },
      {
        "image": "photo_2023-05-27 23.36.06.jpeg",
        "imageS": "photo_2023-05-27 23.36.10.jpeg",
        "imageT": "photo_2023-05-27 23.36.12.jpeg",
        "name": "Ніжна романтична сукня",
        "price": 660,
        "article": "10310",
        "available": true,
        "category": "Сукні",
        "descF": "Якісний натуральний Муслін",
        "descS": "см лхл",
        "descT": "Одеса"
      },
      {
        "image": "photo_2023-05-27 23.42.50.jpeg",
        "imageS": "photo_2023-05-27 23.42.55.jpeg",
        "imageT": "photo_2023-05-27 23.43.00.jpeg",
        "name": "Сукня на шнуровці",
        "price": 500,
        "article": "T3",
        "available": false,
        "category": "Сукні",
        "descF": "Коттон",
        "descS": "42-46, 48-50",
        "descT": "Одеса"
      },
      {
        "image": "photo_2023-05-27 23.46.39.jpeg",
        "imageS": "photo_2023-05-27 23.46.43.jpeg",
        "imageT": "photo_2023-05-27 23.46.52.jpeg",
        "name": "Жіночий костюм з льону",
        "price": 890,
        "article": "076",
        "available": true,
        "category": "Костюми",
        "descF": "Льон",
        "descS": "42-44. 46-48",
        "descT": "Одеса"
      },
      {
        "image": "photo_2023-05-27 23.56.05.jpeg",
        "imageS": "photo_2023-05-27 23.56.05.jpeg",
        "imageT": "photo_2023-05-27 23.56.05.jpeg",
        "name": "Костюм двійка",
        "price": 630,
        "article": "353",
        "available": false,
        "category": "Костюми",
        "descF": "Муслін",
        "descS": "42-44. 46-48",
        "descT": "Одеса"
      },
      {
        "image": "photo_2023-05-28 13.41.36.jpeg",
        "imageS": "photo_2023-05-28 13.41.48.jpeg",
        "imageT": "photo_2023-05-28 13.41.53.jpeg",
        "name": "Брюки жіночі ",
        "price": 490,
        "article": "T6",
        "available": true,
        "category": "Брюки",
        "descF": "Костюмка",
        "descS": "42 - ОС 96 Талія 66 Довжина 108 44 - ОС 100 Талія 74 Довжина 108 46 - ОС 104 Талія 80 Довжина 109 48 - ОС 108 Талія 86 Довжина 109",
        "descT": "Одеса"
      },
      {
        "image": "photo_2023-05-28 13.57.23.jpeg",
        "imageS": "photo_2023-05-28 13.57.29.jpeg",
        "imageT": "photo_2023-05-28 13.57.32.jpeg",
        "name": "Сукня",
        "price": 500,
        "article": "048",
        "available": true,
        "category": "Сукні",
        "descF": "Софт",
        "descS": "42 - 46",
        "descT": "Одеса"
      },
      {
        "image": "photo_2023-05-28 14.01.27.jpeg",
        "imageS": "photo_2023-05-28 14.01.32.jpeg",
        "imageT": "photo_2023-05-28 14.01.47.jpeg",
        "name": "Костюм",
        "price": 590,
        "article": "049",
        "available": true,
        "category": "Костюми",
        "descF": "Kреп жатка",
        "descS": "42 - 46",
        "descT": "Одеса"
      },
      {
        "image": "photo_2023-05-28 14.05.41.jpeg",
        "imageS": "photo_2023-05-28 14.05.47.jpeg",
        "imageT": "photo_2023-05-28 14.05.50.jpeg",
        "name": "Костюм",
        "price": 1090,
        "article": "050",
        "available": true,
        "category": "Костюми",
        "descF": "Двунить , пеньє",
        "descS": "42 - 46",
        "descT": "Одеса"
      }, 
      {
        "image": "photo_2023-05-28 17.13.40.jpeg",
        "imageS": "photo_2023-05-28 17.13.45.jpeg",
        "imageT": "photo_2023-05-28 14.05.50.jpeg",
        "name": "Жіноча трендова блуза з мусліну",
        "price": 490,
        "article": "460",
        "available": true,
        "category": "Блузи",
        "descF": "Муслін високої якості( дуже приємна на дотик)",
        "descS": "42 - 46",
        "descT": "Одеса"
      },
      {
        "image": "photo_2023-05-28 17.19.09.jpeg",
        "imageS": "photo_2023-05-28 17.19.17.jpeg",
        "imageT": "photo_2023-05-28 17.19.23.jpeg",
        "name": "Блуза",
        "price": 540,
        "article": "991",
        "available": true,
        "category": "Блузи",
        "descF": "Софт плотний",
        "descS": "42 - 46",
        "descT": "Одеса"
      },
      {
        "image": "photo_2023-05-28 17.25.14.jpeg",
        "imageS": "photo_2023-05-28 17.25.19.jpeg",
        "imageT": "photo_2023-05-28 17.25.21.jpeg",
        "name": "Блуза",
        "price": 530,
        "article": "971",
        "available": true,
        "category": "Блузи",
        "descF": "Софт",
        "descS": "42 - 46",
        "descT": "Одеса"
      }

    ]
  }